mcp_aliyun_datahub/__init__.py
mcp_aliyun_datahub/__main__.py
mcp_aliyun_datahub/server.py
mcp_aliyun_datahub-0.0.1.dist-info/METADATA
mcp_aliyun_datahub-0.0.1.dist-info/WHEEL
mcp_aliyun_datahub-0.0.1.dist-info/entry_points.txt
mcp_aliyun_datahub-0.0.1.dist-info/RECORD
