Metadata-Version: 2.4
Name: mcp-aliyun-datahub
Version: 0.0.1
Summary: MCP Server based pydatahub for aliyun datahub
Requires-Python: >=3.10
Requires-Dist: build>=1.3.0
Requires-Dist: fastmcp>=2.11.3
Requires-Dist: pydatahub>=2.25.0
Requires-Dist: twine>=6.1.0
